{"name":"Buy laptop","id":"buy;buy-laptop","testSteps":[{"number":1,"description":"Given That the user is on the page","duration":7129,"startTime":"2023-04-10T10:50:33.365-05:00[America/Bogota]","screenshots":[{"screenshot":"bc28f5a491ed46f05363d94f2a6a9e578867665f9b27ae22777541d40cf9ef7a.png","timeStamp":1681141840494}],"result":"SUCCESS","precondition":false,"level":0,"children":[{"number":2,"description":"Open browser","duration":6814,"startTime":"2023-04-10T10:50:33.662-05:00[America/Bogota]","screenshots":[{"screenshot":"bc28f5a491ed46f05363d94f2a6a9e578867665f9b27ae22777541d40cf9ef7a.png","timeStamp":1681141840476}],"result":"SUCCESS","precondition":false,"level":1}]},{"number":3,"description":"When The user logs in","duration":4412,"startTime":"2023-04-10T10:50:40.495-05:00[America/Bogota]","screenshots":[{"screenshot":"34a5e16e8f3d18689a10dbee51d51b01101add084bdef6e837494d0eb9058215.png","timeStamp":1681141844907}],"result":"SUCCESS","precondition":false,"level":0,"children":[{"number":4,"description":"Enter credentials","duration":4382,"startTime":"2023-04-10T10:50:40.508-05:00[America/Bogota]","screenshots":[{"screenshot":"34a5e16e8f3d18689a10dbee51d51b01101add084bdef6e837494d0eb9058215.png","timeStamp":1681141844890}],"result":"SUCCESS","precondition":false,"level":1}]},{"number":5,"description":"And The user makes the purchase","duration":15088,"startTime":"2023-04-10T10:50:44.908-05:00[America/Bogota]","screenshots":[{"screenshot":"372f98d9af98cd31838ed867bbccecab99d2e34cbd929299d5fd8c2c759696bb.png","timeStamp":1681141859996}],"result":"SUCCESS","precondition":false,"level":0,"children":[{"number":6,"description":"Purchase flow","duration":15060,"startTime":"2023-04-10T10:50:44.921-05:00[America/Bogota]","screenshots":[{"screenshot":"372f98d9af98cd31838ed867bbccecab99d2e34cbd929299d5fd8c2c759696bb.png","timeStamp":1681141859981}],"result":"SUCCESS","precondition":false,"level":1,"children":[{"number":7,"description":"Click laptop","duration":6330,"startTime":"2023-04-10T10:50:44.940-05:00[America/Bogota]","screenshots":[{"screenshot":"5daaf3c3666b1c5388ee89d4d21c5bd1b82f1f4b82f8c2b1643823d3da4031d5.png","timeStamp":1681141851269}],"result":"SUCCESS","precondition":false,"level":2},{"number":8,"description":"Select laptop","duration":940,"startTime":"2023-04-10T10:50:51.271-05:00[America/Bogota]","screenshots":[{"screenshot":"5daaf3c3666b1c5388ee89d4d21c5bd1b82f1f4b82f8c2b1643823d3da4031d5.png","timeStamp":1681141851283},{"screenshot":"5daaf3c3666b1c5388ee89d4d21c5bd1b82f1f4b82f8c2b1643823d3da4031d5.png","timeStamp":1681141852211}],"result":"SUCCESS","precondition":false,"level":2},{"number":9,"description":"Clic laptop","duration":7752,"startTime":"2023-04-10T10:50:52.213-05:00[America/Bogota]","screenshots":[{"screenshot":"5daaf3c3666b1c5388ee89d4d21c5bd1b82f1f4b82f8c2b1643823d3da4031d5.png","timeStamp":1681141852225},{"screenshot":"372f98d9af98cd31838ed867bbccecab99d2e34cbd929299d5fd8c2c759696bb.png","timeStamp":1681141859965}],"result":"SUCCESS","precondition":false,"level":2}]}]},{"number":10,"description":"Then The user can validate that the purchase has been successful.","duration":5395,"startTime":"2023-04-10T10:50:59.998-05:00[America/Bogota]","screenshots":[{"screenshot":"688714181c23d6d693e0d66774638ae44d4826b8a8275b3fb80d462bd47c2e08.png","timeStamp":1681141865393}],"result":"SUCCESS","precondition":false,"level":0,"children":[{"number":11,"description":"Validation","duration":5363,"startTime":"2023-04-10T10:51:00.015-05:00[America/Bogota]","screenshots":[{"screenshot":"688714181c23d6d693e0d66774638ae44d4826b8a8275b3fb80d462bd47c2e08.png","timeStamp":1681141860160},{"screenshot":"688714181c23d6d693e0d66774638ae44d4826b8a8275b3fb80d462bd47c2e08.png","timeStamp":1681141865378}],"result":"SUCCESS","precondition":false,"level":1}]}],"userStory":{"id":"buy","storyName":"Buy","path":"src/test/resources/features/buy.feature","type":"feature"},"featureTag":{"name":"Features/Buy","type":"feature","displayName":"Features/Buy"},"title":"Buy laptop","backgroundTitle":"","backgroundDescription":"","tags":[{"name":"Buy","type":"feature","displayName":"Buy"}],"startTime":"2023-04-10T10:50:33.307-05:00[America/Bogota]","duration":32087,"projectKey":"","sessionId":"7650cf0311b4e69304ac840dd9936741","driver":"chrome","isManualTestingUpToDate":false,"manual":false,"testSource":"Cucumber","result":"SUCCESS"}